tests/__init__.py
tests/test_iam.py
tests/functional/__init__.py
tests/functional/test_serviceaccount.py
tests/integration/__init__.py
tests/integration/test_serviceaccount.py
tests/unit/__init__.py
tests/unit/test_gcpapi.py
toto9/__init__.py
toto9/cloudresourcemanager.py
toto9/cloudstorage.py
toto9/errors.py
toto9/gcp_api.py
toto9/iam.py
toto9/retryable_exceptions.py
toto9/serviceaccount.py
toto9-0.1.9.dist-info/METADATA
toto9-0.1.9.dist-info/RECORD
toto9-0.1.9.dist-info/WHEEL
toto9-0.1.9.dist-info/top_level.txt
