Metadata-Version: 2.1
Name: toto9
Version: 0.1.9
Summary: The missing GCP Python Client Library
Home-page: https://gitlab.nordstrom.com/public-cloud/toto9
Author: Nordstrom Cloud Engineering
Author-email: cloudengineers@nordstrom.com
License: MIT
Platform: UNKNOWN
Classifier: Programming Language :: Python :: 3
Classifier: License :: OSI Approved :: MIT License
Classifier: Operating System :: OS Independent
Classifier: Natural Language :: English
Requires-Dist: google-api-python-client
Requires-Dist: google-auth
Requires-Dist: google-auth-httplib2
Requires-Dist: retrying
Requires-Dist: httplib2
